{
	"name": "Vimium C",
	"@time": "9/19/2024, 3:22:32 PM",
	"time": 1726773752765,
	"environment": {
		"extension": "2.11.3",
		"platform": "linux",
		"chromium": 128
	},
	"allBrowserUrls": true,
	"exclusionRules": [],
	"grabBackFocus": true,
	"keyLayout": 2,
	"keyMappings": [
		"#!no-check",
		"map gxx closeOtherTabs",
		"map S goBack",
		"map ee LinkHints.activateFocus",
		"map eu LinkHints.activateHover",
		"map s LinkHints.activate",
		"map E LinkHints.unhoverLast",
		"map i LinkHints.activateEdit",
		"map I enterInsertMode",
		"map c LinkHints.click",
		"map gh Vomnibar.activateHistory",
		""
	],
	"linkHintCharacters": "aoeuidsnth",
	"searchUrl": "https://search.brave.com/search?q=",
	"vimSync": true
}
